hoshmap/__init__.py
hoshmap/appearance.py
hoshmap/frozenidict.py
hoshmap/function/__init__.py
hoshmap/function/higherorder.py
hoshmap/function/pandas.py
hoshmap/idict.py
hoshmap/let.py
hoshmap/serialization/__init__.py
hoshmap/serialization/customjson.py
hoshmap/serialization/parsing.py
hoshmap/value/__init__.py
hoshmap/value/cacheableival.py
hoshmap/value/dfival.py
hoshmap/value/ival.py
hoshmap/value/lazyival.py
hoshmap/value/strictival.py
hoshmap-0.220808.0.dist-info/LICENSE
hoshmap-0.220808.0.dist-info/WHEEL
hoshmap-0.220808.0.dist-info/METADATA
hoshmap-0.220808.0.dist-info/RECORD
