Metadata-Version: 2.1
Name: hoshmap
Version: 0.220808.0
Summary: Hosh-based cacheable lazy dict with deterministic predictable universally unique identifiers
License: GPLv3
Author: davips
Author-email: dpsabc@gmail.com
Requires-Python: >=3.10,<4.0
Classifier: License :: Other/Proprietary License
Classifier: Programming Language :: Python :: 3
Classifier: Programming Language :: Python :: 3.10
Provides-Extra: cache
Requires-Dist: hosh (>=1.211228.2,<2.0.0)
Requires-Dist: shelchemy (>=0.220726.6,<0.220727.0); extra == "cache"
